aresource/__init__.py
aresource/manager.py
aresource/resources/__init__.py
aresource/resources/aiohttp/__init__.py
aresource/resources/aiohttp/session.py
aresource/resources/aiohttp/web.py
aresource/resources/files/__init__.py
aresource/resources/files/base.py
aresource/resources/files/bytes.py
aresource/resources/files/hocon.py
aresource/resources/files/ini.py
aresource/resources/files/json.py
aresource/resources/files/path.py
aresource/resources/files/yaml.py
aresource-0.0.2.dist-info/METADATA
aresource-0.0.2.dist-info/WHEEL
aresource-0.0.2.dist-info/RECORD
