Metadata-Version: 2.3
Name: aresource
Version: 0.0.2
Summary: 
Author: Peter Babka
Author-email: 159peter951@gmail.com
Requires-Python: >=3.13, <4.0
Classifier: Programming Language :: Python :: 3
Classifier: Programming Language :: Python :: 3.13
Provides-Extra: aiohttp
Provides-Extra: hocon
Provides-Extra: pyyaml
Requires-Dist: aiohttp (>=3.0.0,<4.0.0) ; extra == "aiohttp"
Requires-Dist: pyhocon (>=0.3.0,<0.4.0) ; extra == "hocon"
Requires-Dist: pyyaml (>=6.0.0,<7.0.0) ; extra == "pyyaml"
Project-URL: Repository, https://github.com/xbabka01/aresource
